{"cameraMode":{"drawMode":0,"name":"Shaded","section":"Shading Mode"},"sceneLighting":false,"audioPlay":false,"sceneViewState":{"m_AlwaysRefresh":false,"showFog":true,"showSkybox":false,"showFlares":true,"showImageEffects":true,"showParticleSystems":true,"showVisualEffectGraphs":true,"m_FxEnabled":true},"in2DMode":false,"pivot":{"x":-62.665287017822269,"y":-45.1086540222168,"z":20.84107780456543},"rotation":{"x":-0.2876734733581543,"y":0.5633491277694702,"z":-0.2180550992488861,"w":-0.7432101964950562},"size":42.720245361328128,"orthographic":false}